semantic_main/__init__.py
semantic_main/autotwin_mapper.py
semantic_main/formal_model_generator.py
semantic_main/resources/config/config.ini
semantic_main/resources/config/croma_mappings.json
semantic_main/resources/config/legoFactory_mappings.json
semantic_main/resources/config/pizzaLineV4_mappings.json
semantic_main/resources/doc/auto_twin_pm.mdj
semantic_main/resources/gen_models/.notempty
semantic_main/resources/upp_resources/.notempty
semantic_main/resources/upp_resources/verify.sh
semantic_main/resources/upp_results/.notempty
semantic_main/resources/upp_templates/.notempty
semantic_main/resources/upp_templates/nta_template.xml
semantic_main/resources/upp_templates/sha_template.xml
semantic_main/semantic_logger/__init__.py
semantic_main/semantic_logger/logger.py
semantic_main/semantic_mgrs/__init__.py
semantic_main/semantic_mgrs/dot2sha.py
semantic_main/semantic_mgrs/semantic_links_identifier.py
semantic_main/semantic_mgrs/sha2upp.py
semantic_main/semantic_model/__init__.py
semantic_main/semantic_model/semantic_link.py
semantic_main/semantic_model/sha.py
sha2dt_semantic_mapper-0.1.9.dist-info/LICENSE.md
sha2dt_semantic_mapper-0.1.9.dist-info/METADATA
sha2dt_semantic_mapper-0.1.9.dist-info/WHEEL
sha2dt_semantic_mapper-0.1.9.dist-info/RECORD
