Metadata-Version: 2.1
Name: sha2dt-semantic-mapper
Version: 0.1.9
Summary: Module to create semantic links between learned SHA features and existing SKG entities
License: LICENSE.md
Author: livialestingi
Author-email: livia.lestingi@polimi.it
Requires-Python: >=3.10,<4.0
Classifier: License :: Other/Proprietary License
Classifier: Programming Language :: Python :: 3
Classifier: Programming Language :: Python :: 3.10
Classifier: Programming Language :: Python :: 3.11
Classifier: Programming Language :: Python :: 3.12
Classifier: Programming Language :: Python :: 3.13
Requires-Dist: graphviz (>=0.20.1,<0.21.0)
Requires-Dist: matplotlib (>=3.9.0,<4.0.0)
Requires-Dist: neo4j (>=5.18.0,<6.0.0)
Requires-Dist: pygraphviz (>=1.12,<2.0)
Requires-Dist: scipy (>=1.14.0,<2.0.0)
Requires-Dist: skg-connector (>=0.1.6,<0.2.0)
